grayscalelib/core/__init__.py
grayscalelib/core/concretepixels.py
grayscalelib/core/discretization.py
grayscalelib/core/encodable.py
grayscalelib/core/numpypixels.py
grayscalelib/core/pixels.py
grayscalelib/core/tests/__init__.py
grayscalelib/core/tests/conftest.py
grayscalelib/core/tests/test_discretization.py
grayscalelib/core/tests/test_pixels.py
grayscalelib_core-0.0.3.dist-info/METADATA
grayscalelib_core-0.0.3.dist-info/WHEEL
grayscalelib_core-0.0.3.dist-info/top_level.txt
grayscalelib_core-0.0.3.dist-info/RECORD
