Metadata-Version: 2.2
Name: grayscalelib.core
Version: 0.0.3
Summary: A protocol for manipulating grayscale data.
Author: Marco Heisig
License: GPL-3.0-or-later
Project-URL: Repository, https://github.com/SandoghdarLab/grayscalelib.core.git
Keywords: grayscale,video,image,pixel
Requires-Python: >=3.11
Requires-Dist: numpy
Provides-Extra: dev
Requires-Dist: isort; extra == "dev"
Requires-Dist: ruff; extra == "dev"
Requires-Dist: pre-commit; extra == "dev"
Provides-Extra: test
Requires-Dist: pytest; extra == "test"
